{
  "modified": "2023-08-10T03:09:14Z",
  "published": "2023-07-24T21:34:25Z",
  "schema_version": "1.5.0",
  "id": "MAL-2023-1312",
  "summary": "Malicious code in synthetics-recorder (npm)",
  "details": "\n---\n_-= Per source details. Do not edit below this line.=-_\n\n## Source: ossf-malware-analysis (e132b465279df9b9432ece358404299922e0051907132baf848320447a551489)\nThe OpenSSF Package Analysis project identified 'synthetics-recorder' @ 9.9.99 (npm) as malicious.\n\nIt is considered malicious because:\n- The package communicates with a domain associated with malicious activity.\n",
  "affected": [
    {
      "package": {
        "ecosystem": "npm",
        "name": "synthetics-recorder"
      },
      "versions": [
        "1.0.0",
        "9.9.99"
      ]
    }
  ],
  "credits": [
    {
      "name": "OpenSSF: Package Analysis",
      "type": "FINDER",
      "contact": [
        "https://github.com/ossf/package-analysis",
        "https://openssf.slack.com/channels/package_analysis"
      ]
    }
  ],
  "database_specific": {
    "malicious-packages-origins": [
      {
        "import_time": "2023-08-10T03:08:03.525744907Z",
        "modified_time": "2023-07-24T21:34:25.737867471Z",
        "sha256": "4c5ce01d02570ad477fe9ce424839ee638ec5e1a8f70681bcd4cf5270d07551e",
        "source": "ossf-malware-analysis",
        "versions": [
          "1.0.0"
        ]
      },
      {
        "import_time": "2023-08-10T03:08:03.648704338Z",
        "modified_time": "2023-07-24T21:36:44.127751772Z",
        "sha256": "e132b465279df9b9432ece358404299922e0051907132baf848320447a551489",
        "source": "ossf-malware-analysis",
        "versions": [
          "9.9.99"
        ]
      }
    ]
  }
}
