{
  "modified": "2023-09-11T19:34:34Z",
  "published": "2023-09-11T19:34:34Z",
  "schema_version": "1.5.0",
  "id": "",
  "summary": "Malicious code in @get-bridge/bridge-string-utils (npm)",
  "details": "The OpenSSF Package Analysis project identified '@get-bridge/bridge-string-utils' @ 99.99.99 (npm) as malicious.\n\nIt is considered malicious because:\n\n- The package communicates with a domain associated with malicious activity.\n\n- The package executes one or more commands associated with malicious behavior.\n",
  "affected": [
    {
      "package": {
        "ecosystem": "npm",
        "name": "@get-bridge/bridge-string-utils"
      },
      "versions": [
        "99.99.99"
      ]
    }
  ],
  "credits": [
    {
      "name": "OpenSSF: Package Analysis",
      "type": "FINDER",
      "contact": [
        "https://github.com/ossf/package-analysis",
        "https://openssf.slack.com/channels/package_analysis"
      ]
    }
  ],
  "database_specific": {
    "malicious-packages-origins": [
      {
        "source": "ossf-package-analysis",
        "sha256": "e69ac01e87147a835e5ab4045ff640d7fa9d2eb636aeb12eef6e1fc1577d021f",
        "import_time": "2023-09-11T20:05:13.996822829Z",
        "modified_time": "2023-09-11T19:34:34Z",
        "versions": [
          "99.99.99"
        ]
      }
    ]
  }
}
