{
  "modified": "2023-10-30T10:26:02Z",
  "published": "2023-10-30T10:26:02Z",
  "schema_version": "1.5.0",
  "id": "",
  "summary": "Malicious code in editor-layer-index (npm)",
  "details": "The OpenSSF Package Analysis project identified 'editor-layer-index' @ 2050.2.4 (npm) as malicious.\n\nIt is considered malicious because:\n\n- The package communicates with a domain associated with malicious activity.\n",
  "affected": [
    {
      "package": {
        "ecosystem": "npm",
        "name": "editor-layer-index"
      },
      "versions": [
        "2050.2.4"
      ]
    }
  ],
  "credits": [
    {
      "name": "OpenSSF: Package Analysis",
      "type": "FINDER",
      "contact": [
        "https://github.com/ossf/package-analysis",
        "https://openssf.slack.com/channels/package_analysis"
      ]
    }
  ],
  "database_specific": {
    "malicious-packages-origins": [
      {
        "source": "ossf-package-analysis",
        "sha256": "980310405cf8a74edb3b623b986fe370a0d6635850fde6c21f311896d66ee0f6",
        "import_time": "2023-10-30T10:34:51.877297126Z",
        "modified_time": "2023-10-30T10:26:02Z",
        "versions": [
          "2050.2.4"
        ]
      }
    ]
  }
}
