{
  "modified": "2023-09-01T12:32:13Z",
  "published": "2023-09-01T12:32:13Z",
  "schema_version": "1.5.0",
  "id": "",
  "summary": "Malicious code in feature-flag-framework (npm)",
  "details": "The OpenSSF Package Analysis project identified 'feature-flag-framework' @ 9.999.0 (npm) as malicious.\n\nIt is considered malicious because:\n\n- The package executes one or more commands associated with malicious behavior.\n",
  "affected": [
    {
      "package": {
        "ecosystem": "npm",
        "name": "feature-flag-framework"
      },
      "versions": [
        "9.999.0"
      ]
    }
  ],
  "credits": [
    {
      "name": "OpenSSF: Package Analysis",
      "type": "FINDER",
      "contact": [
        "https://github.com/ossf/package-analysis",
        "https://openssf.slack.com/channels/package_analysis"
      ]
    }
  ],
  "database_specific": {
    "malicious-packages-origins": [
      {
        "source": "ossf-package-analysis",
        "sha256": "c9eb473825f248e6bd65e0cd726e6f6017ba7377d00c14a64417271636e68bd9",
        "import_time": "2023-09-05T06:05:40.412046769Z",
        "modified_time": "2023-09-01T12:32:13Z",
        "versions": [
          "9.999.0"
        ]
      }
    ]
  }
}
