{
  "modified": "2023-11-06T19:55:42Z",
  "published": "2023-11-06T19:55:42Z",
  "schema_version": "1.5.0",
  "id": "",
  "summary": "Malicious code in tst-atk (npm)",
  "details": "The OpenSSF Package Analysis project identified 'tst-atk' @ 1.2.26 (npm) as malicious.\n\nIt is considered malicious because:\n\n- The package communicates with a domain associated with malicious activity.\n",
  "affected": [
    {
      "package": {
        "ecosystem": "npm",
        "name": "tst-atk"
      },
      "versions": [
        "1.2.26"
      ]
    }
  ],
  "credits": [
    {
      "name": "OpenSSF: Package Analysis",
      "type": "FINDER",
      "contact": [
        "https://github.com/ossf/package-analysis",
        "https://openssf.slack.com/channels/package_analysis"
      ]
    }
  ],
  "database_specific": {
    "malicious-packages-origins": [
      {
        "source": "ossf-package-analysis",
        "sha256": "1723be658bf81bea54f46d217bc54cd366ede3c6265c246f972e8eea469d9e7d",
        "import_time": "2023-11-06T20:05:51.453059416Z",
        "modified_time": "2023-11-06T19:55:42Z",
        "versions": [
          "1.2.26"
        ]
      }
    ]
  }
}
