{
  "modified": "2023-08-10T06:17:48Z",
  "published": "2023-05-03T04:49:41Z",
  "schema_version": "1.5.0",
  "id": "MAL-2023-1222",
  "summary": "Malicious code in kobi--front-helpers (npm)",
  "details": "\n---\n_-= Per source details. Do not edit below this line.=-_\n\n## Source: ossf-package-analysis (5177d79e84b460a9e6e01e3f7ec740846cab3ff8094ccf7fa38232683498d45c)\nThe OpenSSF Package Analysis project identified 'kobi--front-helpers' @ 1.15.0 (npm) as malicious.\n\nIt is considered malicious because:\n- The package communicates with a domain associated with malicious activity.\n- The package executes one or more commands associated with malicious behavior.\n",
  "affected": [
    {
      "package": {
        "ecosystem": "npm",
        "name": "kobi--front-helpers"
      },
      "versions": [
        "1.17.0",
        "1.15.0",
        "1.18.0"
      ]
    }
  ],
  "credits": [
    {
      "name": "OpenSSF: Package Analysis",
      "type": "FINDER",
      "contact": [
        "https://github.com/ossf/package-analysis",
        "https://openssf.slack.com/channels/package_analysis"
      ]
    }
  ],
  "database_specific": {
    "malicious-packages-origins": [
      {
        "import_time": "2023-08-10T06:15:36.229758Z",
        "modified_time": "2023-05-03T05:02:09.60911773Z",
        "sha256": "3694ca55110a46e5d5d4fad699faabe9d12b0586914aff441559379e25e577e0",
        "source": "ossf-package-analysis",
        "versions": [
          "1.17.0"
        ]
      },
      {
        "import_time": "2023-08-10T06:15:35.963745914Z",
        "modified_time": "2023-05-03T04:49:41.602216415Z",
        "sha256": "5177d79e84b460a9e6e01e3f7ec740846cab3ff8094ccf7fa38232683498d45c",
        "source": "ossf-package-analysis",
        "versions": [
          "1.15.0"
        ]
      },
      {
        "import_time": "2023-08-10T06:15:36.501611185Z",
        "modified_time": "2023-05-03T07:46:39.416784547Z",
        "sha256": "7d295a4929833debf79680bed6675effa1b826d285a8d24f501bf48c4c325301",
        "source": "ossf-package-analysis",
        "versions": [
          "1.18.0"
        ]
      }
    ]
  }
}
