{
  "modified": "2023-10-19T04:51:32Z",
  "published": "2023-10-19T04:51:32Z",
  "schema_version": "1.5.0",
  "id": "",
  "summary": "Malicious code in @syska/aca-gui (npm)",
  "details": "The OpenSSF Package Analysis project identified '@syska/aca-gui' @ 99.0.1 (npm) as malicious.\n\nIt is considered malicious because:\n\n- The package communicates with a domain associated with malicious activity.\n",
  "affected": [
    {
      "package": {
        "ecosystem": "npm",
        "name": "@syska/aca-gui"
      },
      "versions": [
        "99.0.1"
      ]
    }
  ],
  "credits": [
    {
      "name": "OpenSSF: Package Analysis",
      "type": "FINDER",
      "contact": [
        "https://github.com/ossf/package-analysis",
        "https://openssf.slack.com/channels/package_analysis"
      ]
    }
  ],
  "database_specific": {
    "malicious-packages-origins": [
      {
        "source": "ossf-package-analysis",
        "sha256": "c88a2fa038c9864d0063096a140938bab7666ba57f989c17106a0a833b4784b8",
        "import_time": "2023-10-19T05:04:47.05374116Z",
        "modified_time": "2023-10-19T04:51:32Z",
        "versions": [
          "99.0.1"
        ]
      }
    ]
  }
}
