{
  "modified": "2023-08-21T20:12:58Z",
  "published": "2023-02-09T18:51:12Z",
  "schema_version": "1.5.0",
  "id": "",
  "summary": "Malicious code in ryptocompare (pypi)",
  "details": "Attacker distributed 900+ malicious packages via PyPi, infecting browsers to manipulate crypto wallet addresses; ongoing threat possible.",
  "affected": [
    {
      "package": {
        "ecosystem": "pypi",
        "name": "ryptocompare"
      },
      "ranges": [
        {
          "type": "SEMVER",
          "events": [
            {
              "introduced": "0"
            }
          ]
        }
      ]
    }
  ],
  "references": [
    {
      "type": "ARTICLE",
      "url": "https://medium.com/checkmarx-security/17-malicious-python-packages-targeting-selenium-users-to-steal-crypto-8d24628ec656"
    }
  ],
  "credits": [
    {
      "name": "Checkmarx",
      "type": "FINDER",
      "contact": [
        "supplychainsecurity@checkmarx.com",
        "https://bit.ly/checkmarx-malicious-packages"
      ]
    }
  ],
  "database_specific": {
    "malicious-packages-origins": [
      {
        "source": "checkmarx",
        "sha256": "fef7e22367d6b20792688bc247df63990ddab8ad63df008accc8cf857cb2c655",
        "import_time": "2023-08-24T14:44:34.08198274Z",
        "modified_time": "2023-08-21T20:12:58Z",
        "ranges": [
          {
            "type": "SEMVER",
            "events": [
              {
                "introduced": "0"
              }
            ]
          }
        ]
      }
    ]
  }
}
