{
  "modified": "2023-08-24T20:12:58Z",
  "published": "2023-02-25T16:24:12Z",
  "schema_version": "1.5.0",
  "id": "",
  "summary": "Malicious code in hackedload (pypi)",
  "details": "EsqueleSquad group published nearly 6000 malicious PyPi and NPM packages, executing spyware and information-stealing malware",
  "affected": [
    {
      "package": {
        "ecosystem": "pypi",
        "name": "hackedload"
      },
      "ranges": [
        {
          "type": "SEMVER",
          "events": [
            {
              "introduced": "0"
            }
          ]
        }
      ]
    }
  ],
  "references": [
    {
      "type": "ARTICLE",
      "url": "https://medium.com/checkmarx-security/the-skeleton-squad-tracing-the-origins-and-scope-of-5000-malicious-packages-on-pypi-7516c16e4da9"
    }
  ],
  "credits": [
    {
      "name": "Checkmarx",
      "type": "FINDER",
      "contact": [
        "supplychainsecurity@checkmarx.com",
        "https://bit.ly/checkmarx-malicious-packages"
      ]
    }
  ],
  "database_specific": {
    "iocs": {
      "urls": [
        "https://dl.dropbox.com/s/tpykidpdjz99202/esquele.exe",
        "https://cdn.discordapp.com/attachments/1090710876639744062/1102575056925761587/bypass2.ps1"
      ]
    },
    "malicious-packages-origins": [
      {
        "source": "checkmarx",
        "sha256": "22a49c1baaaf6972e16008c812a5e9f52a515e5c2c93a9bb390fa15765ed9a46",
        "import_time": "2023-08-24T15:12:09.835411379Z",
        "modified_time": "2023-08-24T20:12:58Z",
        "ranges": [
          {
            "type": "SEMVER",
            "events": [
              {
                "introduced": "0"
              }
            ]
          }
        ]
      }
    ]
  }
}
